mqtt_device/__init__.py
mqtt_device/common/__init__.py
mqtt_device/common/common_log.py
mqtt_device/common/exception.py
mqtt_device/common/resource_finder.py
mqtt_device/common/wait_until_success.py
mqtt_device/common/tests/__init__.py
mqtt_device/common/tests/test_base_client.py
mqtt_device/common/tests/test_client_config.py
mqtt_device/common/tests/test_client_new.py
mqtt_device/common/tests/test_client_with_device_providers.py.bak
mqtt_device/common/tests/test_local_client.py
mqtt_device/common/tests/test_mqtt_client.py
mqtt_device/common/tests/test_topic.py
mqtt_device/common/tests/test_wait_until_success.py
mqtt_device/common/tests/resources/client_config.ini
mqtt_device/core/__init__.py
mqtt_device/core/client/__init__.py
mqtt_device/core/client/client.py
mqtt_device/core/client/mqtt_client.py
mqtt_device/core/device/__init__.py
mqtt_device/core/device/device.py
mqtt_device/core/device/device_collection.py
mqtt_device/core/device/device_factory.py
mqtt_device/core/device/device_property.py
mqtt_device/core/device/event.py
mqtt_device/core/device/type_var.py
mqtt_device/core/device/local/__init__.py
mqtt_device/core/device/local/factory.py.bak
mqtt_device/core/device/local/local_client.py
mqtt_device/core/device/local/local_device.py
mqtt_device/core/device/local/tests/__init__.py
mqtt_device/core/device/local/tests/test_decorator_sandbox.py
mqtt_device/core/device/local/tests/test_device.py
mqtt_device/core/device/local/tests/test_local_client.py
mqtt_device/core/device/local/tests/test_local_client_interpretor.py
mqtt_device/core/device/local/tests/test_local_mouse_tracker_device.py
mqtt_device/core/device/remote/__init__.py
mqtt_device/core/device/remote/remote_client.py
mqtt_device/core/device/remote/remote_device.py
mqtt_device/core/device/remote/tests/__init__.py
mqtt_device/core/device/remote/tests/test.json
mqtt_device/core/device/remote/tests/test_app_client_interp.py
mqtt_device/core/device/remote/tests/test_application_client.py
mqtt_device-1.1.5.dist-info/METADATA
mqtt_device-1.1.5.dist-info/WHEEL
mqtt_device-1.1.5.dist-info/top_level.txt
mqtt_device-1.1.5.dist-info/RECORD
