Metadata-Version: 2.4
Name: mqtt_device
Version: 1.1.5
Author-email: Nicolas DEBRAY <nicknolt@yahoo.fr>
Project-URL: Homepage, https://github.com/nicknolt/mqtt_device
Classifier: Programming Language :: Python
Classifier: Programming Language :: Python :: 3
Requires-Python: >=3.8
Requires-Dist: obsub
Requires-Dist: paho-mqtt>=1.6.1
Requires-Dist: pytz
